remote_sqlitedict.py
remote_sqlitedict-0.4.2.dist-info/LICENSE
remote_sqlitedict-0.4.2.dist-info/METADATA
remote_sqlitedict-0.4.2.dist-info/WHEEL
remote_sqlitedict-0.4.2.dist-info/top_level.txt
remote_sqlitedict-0.4.2.dist-info/RECORD
